CHANGELOG.txt
LICENCE.txt
MANIFEST.in
README.md
setup.py
alchemy_permissions.egg-info/PKG-INFO
alchemy_permissions.egg-info/SOURCES.txt
alchemy_permissions.egg-info/dependency_links.txt
alchemy_permissions.egg-info/top_level.txt
permissions/__init__.py
permissions/crud.py
permissions/enums.py
permissions/fixtures.py
permissions/models.py
permissions/schemas.py
permissions/utils.py