Metadata-Version: 1.0
Name: alchemy-permissions
Version: 0.0.4
Summary: Custom system of roles and permissions
Home-page: UNKNOWN
Author: Alex Demure
Author-email: alexanderdemure@gmail.com
License: MIT
Keywords: fastapi
Platform: UNKNOWN
